[
    {
        "title": "Smash a Guitar",
        "text": "Smashing a guitar of someone singing a love song",
        "id": "937f"
    },
    {
        "title": "Bond with Misfits",
        "text": "Bond with a group of lovable misfists",
        "id": "3dc5"
    },
    {
        "title": "Take on the Bully",
        "text": "Take on the school bully",
        "id": "8a9d"
    },
    {
        "title": "Make out with Hottest Girl",
        "text": "Make out with the hottest girl on campus",
        "id": "e1d8"
    },
    {
        "title": "Pants",
        "text": "Pants someone",
        "id": "d905"
    },
    {
        "title": "Get Pantsed",
        "text": "Getting pantsed by someone (while wearing the standard giant hearts on underwear)",
        "id": "a601"
    },
    {
        "title": "Steal Mascot",
        "text": "Steal a rival school's mascot",
        "id": "74d0"
    },
    {
        "title": "Pledge the Fraternity",
        "text": "Pledge the cool fraternity (but unbeknownst to you, be the target of ridicule, without a chance in hell of ever getting in)",
        "id": "5d52"
    },
    {
        "title": "Create Robot",
        "text": "Create a quirky robot that, once bong water is spilled on its circuitry, will bring it to life, making you the coolest person in school",
        "id": "676a"
    },
    {
        "title": "Ridiculous Situation",
        "text": "Ridiculous situation descending into heavy-handed drama for the illusion of story",
        "id": "4620"
    },
    {
        "title": "Toga",
        "text": "Participate in a toga party",
        "id": "4f1e"
    },
    {
        "title": "Food Fight",
        "text": "FOOD FIGHT!",
        "id": "986d"
    }
]